LICENSE.txt
MANIFEST.in
README.md
setup.cfg
setup.py
rongdaVbaAddinsLight/RDaddins.xlam
rongdaVbaAddinsLight/RecentTime.db
rongdaVbaAddinsLight/__init__.py
rongdaVbaAddinsLight/registerCode.pyd
rongdaVbaAddinsLight/rongdavbaaddinsLight.pyd
rongdaVbaAddinsLight/runregiterCode.py
rongdaVbaAddinsLight/文件处理类模板.xlsx
rongdaVbaAddinsLight.egg-info/PKG-INFO
rongdaVbaAddinsLight.egg-info/SOURCES.txt
rongdaVbaAddinsLight.egg-info/dependency_links.txt
rongdaVbaAddinsLight.egg-info/top_level.txt
rongdaVbaAddinsLight/Function/__init__.py
rongdaVbaAddinsLight/Function/minusFunction.pyd
rongdaVbaAddinsLight/Function/minusFunctionpy.py
rongdaVbaAddinsLight/Ui/__init__.py
rongdaVbaAddinsLight/Ui/rongdaVbaAddinsUi.pyd
rongdaVbaAddinsLight/package/__init__.py
rongdaVbaAddinsLight/package/pyzipper/__init__.py
rongdaVbaAddinsLight/package/pyzipper/__version__.py
rongdaVbaAddinsLight/package/pyzipper/zipfile.py
rongdaVbaAddinsLight/package/pyzipper/zipfile_aes.py