Metadata-Version: 2.1
Name: rongdaVbaAddinsLight
Version: 0.2.0.63
Summary: 纯净版-Excel插件
Home-page: https://alidocs.dingtalk.com/i/p/4oJRz0VRJyvmLZMydy0mV7WvjQn7MG89
Author: qiuxing,wangweidong
Author-email: 17891967090@163.com
Classifier: Programming Language :: Python
Requires-Python: >=3.8
License-File: LICENSE.txt
